[
  {
    "locationID": "00011",
    "location": [
      39.952453,
      -75.25752
    ]
  },
  {
    "locationID": "00014",
    "location": [
      39.961368,
      -75.278544
    ]
  },
  {
    "locationID": "00019",
    "location": [
      39.91028,
      -75.279897
    ]
  },
  {
    "locationID": "00040",
    "location": [
      40.023187,
      -75.230825
    ]
  },
  {
    "locationID": "00055",
    "location": [
      39.954534,
      -75.19492
    ]
  },
  {
    "locationID": "00073",
    "location": [
      39.941014,
      -75.272307
    ]
  },
  {
    "locationID": "00084",
    "location": [
      40.063243,
      -75.086025
    ]
  },
  {
    "locationID": "00086",
    "location": [
      39.955203,
      -75.168362
    ]
  },
  {
    "locationID": "00103",
    "location": [
      39.948251,
      -75.156673
    ]
  },
  {
    "locationID": "00115",
    "location": [
      40.03623,
      -75.070283
    ]
  },
  {
    "locationID": "00119",
    "location": [
      39.983697,
      -75.100734
    ]
  },
  {
    "locationID": "00125",
    "location": [
      40.060799,
      -75.192028
    ]
  },
  {
    "locationID": "00155",
    "location": [
      40.018696,
      -75.240128
    ]
  },
  {
    "locationID": "00161",
    "location": [
      39.962279,
      -75.173052
    ]
  },
  {
    "locationID": "00179",
    "location": [
      39.95107,
      -75.19898
    ]
  },
  {
    "locationID": "00181",
    "location": [
      40.064166,
      -75.054416
    ]
  },
  {
    "locationID": "00183",
    "location": [
      40.046348,
      -75.070241
    ]
  },
  {
    "locationID": "00191",
    "location": [
      39.926449,
      -75.145403
    ]
  },
  {
    "locationID": "00193",
    "location": [
      40.022155,
      -75.062657
    ]
  },
  {
    "locationID": "00207",
    "location": [
      40.0053,
      -75.102819
    ]
  },
  {
    "locationID": "00240",
    "location": [
      40.01894,
      -75.097093
    ]
  },
  {
    "locationID": "00247",
    "location": [
      39.941882,
      -75.145875
    ]
  },
  {
    "locationID": "00252",
    "location": [
      39.996524,
      -75.074405
    ]
  },
  {
    "locationID": "00276",
    "location": [
      40.074888,
      -75.084276
    ]
  },
  {
    "locationID": "00294",
    "location": [
      40.012227,
      -75.261996
    ]
  },
  {
    "locationID": "00317",
    "location": [
      39.877038,
      -75.110918
    ]
  },
  {
    "locationID": "00352",
    "location": [
      39.916361,
      -75.070071
    ]
  },
  {
    "locationID": "00392",
    "location": [
      39.833123,
      -75.062225
    ]
  },
  {
    "locationID": "00396",
    "location": [
      39.864862,
      -75.099798
    ]
  },
  {
    "locationID": "00427",
    "location": [
      39.843378,
      -75.144143
    ]
  },
  {
    "locationID": "00468",
    "location": [
      39.913042,
      -75.056322
    ]
  },
  {
    "locationID": "00477",
    "location": [
      39.9007,
      -75.076245
    ]
  },
  {
    "locationID": "00480",
    "location": [
      39.84706,
      -75.183434
    ]
  },
  {
    "locationID": "00730",
    "location": [
      39.890466,
      -75.065499
    ]
  },
  {
    "locationID": "00778",
    "location": [
      39.88779,
      -75.111079
    ]
  },
  {
    "locationID": "00779",
    "location": [
      39.852337,
      -75.125646
    ]
  },
  {
    "locationID": "00932",
    "location": [
      39.856293,
      -75.076237
    ]
  },
  {
    "locationID": "00965",
    "location": [
      39.934667,
      -75.068786
    ]
  },
  {
    "locationID": "00972",
    "location": [
      39.886885,
      -75.087223
    ]
  },
  {
    "locationID": "00990",
    "location": [
      39.964236,
      -75.050515
    ]
  },
  {
    "locationID": "08006",
    "location": [
      40.055714,
      -75.090448
    ]
  },
  {
    "locationID": "08007",
    "location": [
      39.904407,
      -75.28281
    ]
  },
  {
    "locationID": "08009",
    "location": [
      40.030026,
      -75.05618
    ]
  },
  {
    "locationID": "08013",
    "location": [
      39.977163,
      -75.118437
    ]
  },
  {
    "locationID": "08049",
    "location": [
      40.040688,
      -75.223496
    ]
  },
  {
    "locationID": "08052",
    "location": [
      40.04015,
      -75.057231
    ]
  },
  {
    "locationID": "08053",
    "location": [
      39.891155,
      -75.241928
    ]
  },
  {
    "locationID": "08065",
    "location": [
      39.997046,
      -75.088803
    ]
  },
  {
    "locationID": "08069",
    "location": [
      39.949165,
      -75.16394
    ]
  },
  {
    "locationID": "08070",
    "location": [
      39.965574,
      -75.280898
    ]
  },
  {
    "locationID": "08087",
    "location": [
      40.05435,
      -75.04948
    ]
  },
  {
    "locationID": "08093",
    "location": [
      39.953317,
      -75.172822
    ]
  },
  {
    "locationID": "08104",
    "location": [
      40.012341,
      -75.068497
    ]
  },
  {
    "locationID": "08105",
    "location": [
      39.945345,
      -75.178594
    ]
  },
  {
    "locationID": "08112",
    "location": [
      39.9518336326,
      -75.1598673308
    ]
  },
  {
    "locationID": "08113",
    "location": [
      39.950443,
      -75.161938
    ]
  },
  {
    "locationID": "08131",
    "location": [
      39.949084,
      -75.150854
    ]
  },
  {
    "locationID": "08141",
    "location": [
      39.955459,
      -75.191319
    ]
  },
  {
    "locationID": "08144",
    "location": [
      39.942713,
      -75.157297
    ]
  },
  {
    "locationID": "08336",
    "location": [
      39.936551,
      -75.048525
    ]
  },
  {
    "locationID": "08340",
    "location": [
      39.871837,
      -75.045252
    ]
  }
]